git_gone/__init__.py
git_gone/__main__.py
git_gone/source.py
git_gone/synchronise.py
git_gone-2.2.2.dist-info/entry_points.txt
git_gone-2.2.2.dist-info/WHEEL
git_gone-2.2.2.dist-info/METADATA
git_gone-2.2.2.dist-info/RECORD
